MANIFEST.in
README.txt
setup.py
docs/HISTORY.txt
silva/__init__.py
silva.pageactions.pdf.egg-info/PKG-INFO
silva.pageactions.pdf.egg-info/SOURCES.txt
silva.pageactions.pdf.egg-info/dependency_links.txt
silva.pageactions.pdf.egg-info/namespace_packages.txt
silva.pageactions.pdf.egg-info/not-zip-safe
silva.pageactions.pdf.egg-info/requires.txt
silva.pageactions.pdf.egg-info/top_level.txt
silva/pageactions/__init__.py
silva/pageactions/pdf/__init__.py
silva/pageactions/pdf/configure.zcml
silva/pageactions/pdf/pdf.py
silva/pageactions/pdf/pdf_templates/pdfaction.cpt