Metadata-Version: 1.1
Name: silva.pageactions.pdf
Version: 1.0.1
Summary: Create a PDF out of the current page in Silva CMS
Home-page: https://github.com/silvacms/silva.pageactions.pdf
Author: Infrae
Author-email: info@infrae.com
License: BSD
Keywords: silva page actions pdf
Platform: UNKNOWN
Classifier: Framework :: Zope2
Classifier: Programming Language :: Python
Classifier: Topic :: Software Development :: Libraries :: Python Modules
